{
  "parent": "minecraft:recipes/root",
  "rewards": {
    "recipes": [
      "survive:green_washcloth"
    ]
  },
  "criteria": {
    "has_white_washcloth": {
      "trigger": "minecraft:inventory_changed",
      "conditions": {
        "items": [
          {
            "item": "survive:white_washcloth"
          }
        ]
      }
    },
    "has_the_recipe": {
      "trigger": "minecraft:recipe_unlocked",
      "conditions": {
        "recipe": "survive:green_washcloth"
      }
    }
  },
  "requirements": [
    [
      "has_white_washcloth",
      "has_the_recipe"
    ]
  ]
}